git_dct/__init__.py
git_dct/__main__.py
git_dct/assets/__init__.py
git_dct/assets/alias.gitconfig
git_dct/cli/__init__.py
git_dct/cli/entrypoint.py
git_dct/cli/main.py
git_dct/package/__init__.py
git_dct/package/bundle.py
git_dct/package/settings.py
git_dct/package/updates.py
git_dct/package/version.py
git_dct/prints/__init__.py
git_dct/prints/boxes.py
git_dct/prints/colors.py
git_dct/system/__init__.py
git_dct/system/platform.py
git_dct/tools/__init__.py
git_dct/tools/git_cauthor.py
git_dct/tools/git_dashboard_panel.py
git_dct/tools/git_fcp.py
git_dct/tools/git_fe.py
git_dct/tools/git_foreach.py
git_dct/tools/git_pu.py
git_dct/tools/git_rb.py
git_dct/tools/git_stat.py
git_dct/tools/tools.py
git_dct/types/__init__.py
git_dct/types/strings.py
git_dct-4.0.0.dist-info/licenses/LICENSE
git_dct-4.0.0.dist-info/METADATA
git_dct-4.0.0.dist-info/WHEEL
git_dct-4.0.0.dist-info/entry_points.txt
git_dct-4.0.0.dist-info/top_level.txt
git_dct-4.0.0.dist-info/RECORD
