Metadata-Version: 2.4
Name: git-dct
Version: 4.0.0
Summary: Git development CLI tools for daily usage
Home-page: https://gitlab.com/RadianDevCore/tools/git-dct
Author: Adrian DC
Author-email: radian.dc@gmail.com
License: Apache License 2.0
Project-URL: Bug Reports, https://gitlab.com/RadianDevCore/tools/git-dct/-/issues
Project-URL: Changelog, https://gitlab.com/RadianDevCore/tools/git-dct/blob/main/CHANGELOG.md
Project-URL: Documentation, https://gitlab.com/RadianDevCore/tools/git-dct#git-dct
Project-URL: Source, https://gitlab.com/RadianDevCore/tools/git-dct
Project-URL: Statistics, https://pypistats.org/packages/git-dct
Keywords: git git-dct
Classifier: Environment :: Console
Classifier: Intended Audience :: Developers
Classifier: License :: OSI Approved :: Apache Software License
Classifier: Operating System :: OS Independent
Classifier: Programming Language :: Python :: 3
Classifier: Programming Language :: Python :: 3.9
Classifier: Programming Language :: Python :: 3.10
Classifier: Programming Language :: Python :: 3.11
Classifier: Programming Language :: Python :: 3.12
Classifier: Programming Language :: Python :: 3.13
Classifier: Topic :: Software Development
Classifier: Topic :: Utilities
Requires-Python: >=3,!=3.0.*,!=3.1.*,!=3.2.*,!=3.3.*,!=3.4.*,!=3.5.*,!=3.6.*,!=3.7.*
License-File: LICENSE
Requires-Dist: colored>=1.4.2
Requires-Dist: importlib-metadata>=8.5.0
Requires-Dist: packaging>=24.0
Requires-Dist: questionary>=2.1.1
Requires-Dist: setuptools>=45.1.0
Requires-Dist: update_checker>=0.18.0
Dynamic: author
Dynamic: author-email
Dynamic: classifier
Dynamic: description
Dynamic: description-content-type
Dynamic: home-page
Dynamic: keywords
Dynamic: license
Dynamic: license-file
Dynamic: project-url
Dynamic: requires-dist
Dynamic: requires-python
Dynamic: summary
